ADAMModbusDriver/AdamClient.py
ADAMModbusDriver/__init__.py
ADAMModbusDriver-0.19.0.dist-info/METADATA
ADAMModbusDriver-0.19.0.dist-info/WHEEL
ADAMModbusDriver-0.19.0.dist-info/top_level.txt
ADAMModbusDriver-0.19.0.dist-info/RECORD
