Metadata-Version: 2.1
Name: ADAMModbusDriver
Version: 0.19.0
Summary: A Python client for interfacing with Adam devices via ModbusTCP
Home-page: https://github.com/spanio/ADAM-driver
Author: Brian Benchoff
Author-email: brian.benchoff@span.io
Classifier: Development Status :: 3 - Alpha
Classifier: Intended Audience :: Developers
Classifier: License :: OSI Approved :: MIT License
Classifier: Programming Language :: Python :: 3.6
Classifier: Programming Language :: Python :: 3.7
Classifier: Programming Language :: Python :: 3.8
Classifier: Programming Language :: Python :: 3.9
Classifier: Topic :: Software Development :: Libraries :: Python Modules
Requires-Dist: pyModbusTCP >=0.1.8
Requires-Dist: pymodbus >=2.5.3
